pyfunc_native.cp313-win_amd64.pyd
pyfunc/__init__.py
pyfunc/bitwise.py
pyfunc/errors.py
pyfunc/pipeline.py
pyfunc/placeholder.py
pyfunc/statistics.py
pyfunc/utils.py
pyfunc/backends/__init__.py
pyfunc/backends/backend_selector.py
pyfunc/backends/cpp_backend.py
pyfunc/backends/go_backend.py
pyfunc/backends/python_backend.py
pyfunc/backends/rust_backend.py
pyfunc/backends/zig_backend.py
pyfunc/native/bindings.cpp
pyfunc/native/operations.cpp
pyfunc/native/operations.hpp
pyfunc/native_go/__init__.py
pyfunc/native_go/native_go.dll
pyfunc/native_go/native_go.h
pyfunc_pipeline-0.4.0.dist-info/licenses/LICENSE
pyfunc_pipeline-0.4.0.dist-info/METADATA
pyfunc_pipeline-0.4.0.dist-info/WHEEL
pyfunc_pipeline-0.4.0.dist-info/top_level.txt
pyfunc_pipeline-0.4.0.dist-info/RECORD
