Metadata-Version: 2.4
Name: pyfunc-pipeline
Version: 0.4.0
Summary: Functional programming pipeline for Python with chainable operations, lazy evaluation, and elegant placeholder syntax
Author-email: Alex <alex@example.com>
Maintainer-email: Alex <alex@example.com>
License: MIT
Project-URL: Homepage, https://github.com/alexzzzs/PyFunc
Project-URL: Documentation, https://github.com/alexzzzs/PyFunc/blob/master/DOCUMENTATION.md
Project-URL: Repository, https://github.com/alexzzzs/PyFunc
Project-URL: Bug Tracker, https://github.com/alexzzzs/PyFunc/issues
Project-URL: Changelog, https://github.com/alexzzzs/PyFunc/blob/master/CHANGELOG.md
Keywords: functional,pipeline,data,transformation,lazy,evaluation,placeholder
Classifier: Development Status :: 4 - Beta
Classifier: Intended Audience :: Developers
Classifier: Operating System :: OS Independent
Classifier: Programming Language :: Python :: 3
Classifier: Programming Language :: Python :: 3.8
Classifier: Programming Language :: Python :: 3.9
Classifier: Programming Language :: Python :: 3.10
Classifier: Programming Language :: Python :: 3.11
Classifier: Programming Language :: Python :: 3.12
Classifier: Topic :: Software Development :: Libraries :: Python Modules
Classifier: Topic :: Utilities
Classifier: Typing :: Typed
Requires-Python: >=3.8
License-File: LICENSE
Provides-Extra: dev
Requires-Dist: pytest>=6.0; extra == "dev"
Requires-Dist: mypy>=0.900; extra == "dev"
Requires-Dist: black>=21.0; extra == "dev"
Requires-Dist: flake8>=3.8; extra == "dev"
Dynamic: license-file
